lilush_llm_backend/__init__.py
lilush_llm_backend/generation.py
lilush_llm_backend/loader.py
lilush_llm_backend/mixin.py
lilush_llm_backend/server.py
lilush_llm_backend-0.1.4.dist-info/LICENSE
lilush_llm_backend-0.1.4.dist-info/WHEEL
lilush_llm_backend-0.1.4.dist-info/METADATA
lilush_llm_backend-0.1.4.dist-info/RECORD
